gobblet_rl/__init__.py
gobblet_rl/__version__.py
gobblet_rl/examples/__init__.py
gobblet_rl/examples/example_RLlib.py
gobblet_rl/examples/example_RLlib_selfplay.py
gobblet_rl/examples/example_RLlib_v1.py
gobblet_rl/examples/example_basic.py
gobblet_rl/examples/example_record_game.py
gobblet_rl/examples/example_stable_baselines3.py
gobblet_rl/examples/example_tianshou_DQN.py
gobblet_rl/examples/example_tianshou_greedy.py
gobblet_rl/examples/example_user_input.py
gobblet_rl/game/__init__.py
gobblet_rl/game/board.py
gobblet_rl/game/collector_manual_policy.py
gobblet_rl/game/gobblet.py
gobblet_rl/game/greedy_policy.py
gobblet_rl/game/greedy_policy_rllib.py
gobblet_rl/game/greedy_policy_tianshou.py
gobblet_rl/game/img/GobbletBoard3x3.png
gobblet_rl/game/img/GobbletLargeRed.png
gobblet_rl/game/img/GobbletLargeRedPreview.png
gobblet_rl/game/img/GobbletLargeYellow.png
gobblet_rl/game/img/GobbletMedRed.png
gobblet_rl/game/img/GobbletMedYellow.png
gobblet_rl/game/img/GobbletSmallRed.png
gobblet_rl/game/img/GobbletSmallYellow.png
gobblet_rl/game/img/GobbletXLRed.png
gobblet_rl/game/img/GobbletXLYellow.png
gobblet_rl/game/img/gobbletboard4x4.png
gobblet_rl/game/img/preview/GobbleXLRedPreview.png
gobblet_rl/game/img/preview/GobbletLargeRedPreview.png
gobblet_rl/game/img/preview/GobbletLargeYellowPreview.png
gobblet_rl/game/img/preview/GobbletMedRedPreview.png
gobblet_rl/game/img/preview/GobbletMedYellowPreview.png
gobblet_rl/game/img/preview/GobbletSmallRedPreview.png
gobblet_rl/game/img/preview/GobbletSmallYellowPreview.png
gobblet_rl/game/img/preview/GobbletXLYellowPreview.png
gobblet_rl/game/manual_policy.py
gobblet_rl/game/random_admissible_policy_rllib.py
gobblet_rl/game/utils.py
gobblet_rl/gobblet_rl.egg-info/PKG-INFO
gobblet_rl/gobblet_rl.egg-info/SOURCES.txt
gobblet_rl/gobblet_rl.egg-info/dependency_links.txt
gobblet_rl/gobblet_rl.egg-info/requires.txt
gobblet_rl/gobblet_rl.egg-info/top_level.txt
gobblet_rl/gobblet_v1.py
gobblet_rl-1.3.5.dist-info/LICENSE
gobblet_rl-1.3.5.dist-info/METADATA
gobblet_rl-1.3.5.dist-info/WHEEL
gobblet_rl-1.3.5.dist-info/RECORD
