Metadata-Version: 2.1
Name: gobblet-rl
Version: 1.3.5
Summary: Interactive Multi-Agent Reinforcement Learning Environment for the board game Gobblet using PettingZoo.
Home-page: https://github.com/elliottower/gobblet-rl/
License: MIT
Keywords: gobblet,board game,multiagent-reinforcement-learning,pettingzoo,gymnasium,interactive,pygame
Author: elliottower
Author-email: elliot@elliottower.com
Requires-Python: >=3.8,<3.12
Classifier: Intended Audience :: Science/Research
Classifier: License :: OSI Approved :: MIT License
Classifier: Operating System :: OS Independent
Classifier: Programming Language :: Python :: 3
Classifier: Programming Language :: Python :: 3.8
Classifier: Programming Language :: Python :: 3.9
Classifier: Programming Language :: Python :: 3.10
Classifier: Programming Language :: Python :: 3.11
Classifier: Programming Language :: Python :: 3
Classifier: Programming Language :: Python :: 3.8
Classifier: Topic :: Scientific/Engineering :: Artificial Intelligence
Requires-Dist: PettingZoo (>=1.22.3,<2.0.0)
Requires-Dist: SuperSuit (>=3.7.1,<4.0.0)
Requires-Dist: gymnasium (>=0.27.1,<0.28.0)
Requires-Dist: numpy (>=1.23.0,<2.0.0)
Requires-Dist: poetry (>=1.3.2,<2.0.0)
Requires-Dist: pygame (>=2.1.3,<3.0.0)
Project-URL: Bug Tracker, https://github.com/elliottower/gobblet-rl/issues
Project-URL: Repository, https://github.com/elliottower/gobblet-rl/
